README.rst
setup.py
gtable/__init__.py
gtable/column.py
gtable/fast.py
gtable/joins.py
gtable/lib.py
gtable/reductions.py
gtable/table.py
gtable/version.py
gtable.egg-info/PKG-INFO
gtable.egg-info/SOURCES.txt
gtable.egg-info/dependency_links.txt
gtable.egg-info/requires.txt
gtable.egg-info/top_level.txt