Metadata-Version: 1.1
Name: gtable
Version: 1.1.0
Summary: A fast table-like container for data analytics
Home-page: UNKNOWN
Author: Guillem Borrell
Author-email: guillemborrell@gmail.com
License: Revised BSD-3 Clause
Platform: UNKNOWN
Classifier: Development Status :: 5 - Production/Stable
Classifier: Intended Audience :: Developers
Classifier: License :: OSI Approved :: BSD License
Classifier: Natural Language :: English
Classifier: Programming Language :: Python :: 3 :: Only
